framecheck/__init__.py
framecheck/column_checks.py
framecheck/dataframe_checks.py
framecheck/frame_check.py
framecheck/function_registry.py
framecheck/persistence.py
framecheck/utilities.py
tests/__init__.py
tests/test_column_checks.py
tests/test_comprehensive_integration.py
tests/test_dataframe_checks.py
tests/test_framecheck_integration.py
tests/test_logging.py
tests/test_persistence.py
tests/test_persistence_integration.py
tests/test_schema.py
tests/test_utilities.py
tests/test_validation_result.py
framecheck-0.5.1.dist-info/METADATA
framecheck-0.5.1.dist-info/WHEEL
framecheck-0.5.1.dist-info/top_level.txt
framecheck-0.5.1.dist-info/RECORD
