Metadata-Version: 2.1
Name: framecheck
Version: 0.5.1
Summary: Lightweight, readable, and extensible validation for pandas DataFrames.
Home-page: https://github.com/OlivierNDO/framecheck/
Author: Nick Olivier
Author-email: Nick Olivier <olivier_n@alum.lynchburg.edu>
License: MIT
Project-URL: Homepage, https://github.com/OlivierNDO/framecheck
Project-URL: Documentation, https://github.com/OlivierNDO/framecheck#readme
Project-URL: Issues, https://github.com/OlivierNDO/framecheck/issues
Requires-Python: >=3.8
Requires-Dist: pandas>=1.3
